python_calculus/__init__.py
python_calculus/cli.py
python_calculus/python_calculus.py
python_calculus-0.1.0.dist-info/DESCRIPTION.rst
python_calculus-0.1.0.dist-info/METADATA
python_calculus-0.1.0.dist-info/RECORD
python_calculus-0.1.0.dist-info/WHEEL
python_calculus-0.1.0.dist-info/entry_points.txt
python_calculus-0.1.0.dist-info/metadata.json
python_calculus-0.1.0.dist-info/top_level.txt
