Metadata-Version: 2.0
Name: python-calculus
Version: 0.1.0
Summary: do derivatives like a charm
Home-page: https://github.com/KapilKhanal/python_calculus
Author: Kapil Khanal
Author-email: kkhanal16@winona.edu
License: MIT license
Keywords: python_calculus
Platform: UNKNOWN
Classifier: Development Status :: 2 - Pre-Alpha
Classifier: Intended Audience :: Developers
Classifier: License :: OSI Approved :: MIT License
Classifier: Natural Language :: English
Classifier: Programming Language :: Python :: 2
Classifier: Programming Language :: Python :: 2.6
Classifier: Programming Language :: Python :: 2.7
Classifier: Programming Language :: Python :: 3
Classifier: Programming Language :: Python :: 3.3
Classifier: Programming Language :: Python :: 3.4
Classifier: Programming Language :: Python :: 3.5
Requires-Dist: Click (>=6.0)
